{"basics":{"name":"Yuman Gao","image":"","email":"ymgao@zju.edu.cn","phone":"(+86) 13688187636","url":"https://si-lhouette.github.io/","summary":["Ph.D. student in Robotics at FASTLab, Zhejiang University \\ ","Visiting Student Scholar at Hybrid Robotics Group, UC Berkeley"],"location":{"address":"2712 Broadway St","postalCode":"CA 94115","city":"San Francisco","countryCode":"US","region":"California"},"profiles":[{"network":"Twitter","username":"AlbertEinstein","url":"https://twitter.com/AlbertEinstein"}]},"education":[{"institution":"University of California, Berkeley","location":"California, U.S.","url":"https://www.berkeley.edu/","area":"Hybrid Robotics Group, Mechanical Engineering","studyType":"Research Student Scholar","startDate":"2024-12","endDate":"2025-12"},{"institution":"Zhejiang University, China","location":"Zhejiang, China","url":"https://www.zju.edu.cn/english/","area":"FASTLab, Control Science","studyType":"Ph.D.","startDate":"2021-09","endDate":"2026-06"},{"institution":"Zhejiang University, China","location":"Zhejiang, China","url":"https://www.zju.edu.cn/english/","area":["Control Science","\\ ACEE (Advanced Honor Class of Engineering Education) at Chu Kochen Honors College"],"studyType":"Bachelor","startDate":"2017-09","endDate":"2021-06"}],"work":[{"name":"DJI","position":"Planning and Control Engineer","url":"https://example.com","startDate":"2022-03","endDate":"2023-03","summary":"Vehicle-mounted quadrotor project"}],"awards":[{"title":"Zhejiang University Outstanding Student","date":"2023","awarder":"Zhejiang University"},{"title":"CHUNHUI Scholarship","date":"2021","awarder":"Zhejiang University","summary":"Top 2%"},{"title":"Mathematical Contest in Modeling","date":"2021","awarder":"China Society for Industrial and Applied Mathematics","summary":"First Prize (Notional level, China) (Top 0.7%)"}],"publications":[{"name":"Adaptive tracking and perching for quadrotor in dynamic scenarios","publisher":"T-RO","releaseDate":"2023","url":"https://ieeexplore.ieee.org/abstract/document/10328688","summary":"planning algorithm to generate track and perch trajectories in dynamic scenarios."}],"skills":[{"name":"Robotics","icon":"fa-solid fa-hashtag","keywords":["C++","Python","MATLAB","ROS","SolidWorks"]},{"name":"Design","icon":"fa-solid fa-hashtag","keywords":["Pr","Keyshot","Unity"]}],"interests":[{"name":"Robotics","icon":"fa-solid fa-tag","keywords":["Motion Planning","Multi-robot System"]}]}